src/eeg_preprocessing_cst/__init__.py
src/eeg_preprocessing_cst/pipeline.py
eeg_preprocessing_cst-0.1.0.dist-info/LICENSE
eeg_preprocessing_cst-0.1.0.dist-info/METADATA
eeg_preprocessing_cst-0.1.0.dist-info/WHEEL
eeg_preprocessing_cst-0.1.0.dist-info/RECORD
