Metadata-Version: 2.1
Name: eeg_preprocessing_cst
Version: 0.1.0
Summary: Preprocessing pipeline for the CST dataset at Nathan Kline Institute
License: LGPL-3.0
Author: Samuel Louviot
Author-email: sam.louviot@gmail.com
Requires-Python: >=3.9,<4.0
Classifier: License :: OSI Approved :: GNU Lesser General Public License v3 (LGPLv3)
Classifier: Programming Language :: Python :: 3
Classifier: Programming Language :: Python :: 3.9
Classifier: Programming Language :: Python :: 3.10
Classifier: Programming Language :: Python :: 3.11
Classifier: Programming Language :: Python :: 3.12
